[
    {
        "name": "android-development.md",
        "date": "2013-10-16"
    },
    {
        "name": "weekly-update-1.md",
        "date": "2013-10-31"
    },
    {
        "name": "weekly-update-2.md",
        "date": "2013-11-03"
    },
    {
        "name": "weekly-update-3.md",
        "date": "2013-11-11"
    },
    {
        "name": "weekly-update-4.md",
        "date": "2013-11-19"
    },
    {
        "name": "weekly-update-5.md",
        "date": "2013-11-27"
    },
    {
        "name": "weekly-update-6.md",
        "date": "2013-12-04"
    },
    {
        "name": "weekly-update-7.md",
        "date": "2014-01-27"
    },
    {
        "name": "daily-update-1.md",
        "date": "2014-01-27"
    },
    {
        "name": "daily-update-2.md",
        "date": "2014-01-28"
    },
    {
        "name": "daily-update-3.md",
        "date": "2014-01-29"
    },
    {
        "name": "new-OS.md",
        "date": "2014-02-27"
    },
    {
        "name": "server-migration-starbound.md",
        "date": "2014-03-05"
    },
    {
        "name": "sunrise.md",
        "date": "2014-06-14"
    },
    {
        "name": "long-time-no-post.md",
        "date": "2014-10-20"
    },
    {
        "name": "a-brief-update.md",
        "date": "2015-01-12"
    }
]
